NSFastHttp/Compare.py
NSFastHttp/DbHelper.py
NSFastHttp/FastRequest.py
NSFastHttp/__about__.py
NSFastHttp/__init__.py
NSFastHttp/Har2Template/__init__.py
NSFastHttp/Har2Template/cli.py
NSFastHttp/Har2Template/compat.py
NSFastHttp/Har2Template/core.py
NSFastHttp/Har2Template/utils.py
NSFastHttp-0.0.3.dist-info/METADATA
NSFastHttp-0.0.3.dist-info/WHEEL
NSFastHttp-0.0.3.dist-info/entry_points.txt
NSFastHttp-0.0.3.dist-info/top_level.txt
NSFastHttp-0.0.3.dist-info/RECORD
