Metadata-Version: 2.1
Name: NSFastHttp
Version: 0.0.3
Summary: NSFastHttp package
Home-page: https://github.com/gawen-ma/NSFastHttp
Author: Gawen
Author-email: mawengang@nsfocus.com
License: MIT
Platform: UNKNOWN
Classifier: License :: OSI Approved :: MIT License
Classifier: Operating System :: OS Independent
Requires-Python: >=2.7, <=3
